PokemonLibrary/__init__.py
PokemonLibrary/pokemon.csv
PokemonLibrary/random_pokemon.py
PokemonLibrary-1.0.3.dist-info/METADATA
PokemonLibrary-1.0.3.dist-info/WHEEL
PokemonLibrary-1.0.3.dist-info/top_level.txt
PokemonLibrary-1.0.3.dist-info/RECORD
