Metadata-Version: 2.1
Name: PokemonLibrary
Version: 1.0.3
Summary: Una biblioteca que contiene la clase RandomPokemon
Author: Martha Morales
Author-email: martha_morales@live.com.mx
Requires-Dist: pandas
